{
  "recording": {
    "name": "300000001241948-300000001731564-3145815176 by charles@superbalife.com @ 10_47_43 AM.wav",
    "size": 120506,
    "modifyTime": 1771008560000,
    "remotePath": "/five9sftp/upload/SB CS/2_13_2026/300000001241948-300000001731564-3145815176 by charles@superbalife.com @ 10_47_43 AM.wav",
    "uploadDate": "2026-02-13T18:49:20.000Z",
    "callId": "300000001241948-300000001731564",
    "agent": "charles",
    "phoneNumber": "3145815176",
    "callTimestamp": "2026-02-13T10:47:43.000Z",
    "campaign": "test one",
    "audioUrl": "https://sfo3.digitaloceanspaces.com/spaces-bucket/five9-recordings/2026-02-13_charles_300000001241948-300000001731564_3145815176.wav",
    "transcriptUrl": "https://sfo3.digitaloceanspaces.com/spaces-bucket/five9-recordings/2026-02-13_charles_300000001241948-300000001731564_3145815176.txt"
  },
  "transcription": {
    "text": "Speaker 1: Thanks for calling Viagra, this is Charles.\n\nSpeaker 2: Hi Charles, I ordered some Viagra AGB and it's telling me, I filled out all the information and it's telling me they need a 5 second video of me and I'm not smart enough how to figure out how to send you a 5 minute or 5 second video of me.\n\nSpeaker 1: Oh good.\n\nSpeaker 2: So they'll call the doctor or whatever and...\n\nSpeaker 1: Yeah, let me do that for you, this is Kenton Doonman, right?\n\nSpeaker 2: That's correct.\n\nSpeaker 1: Okay, please call at the end of the day today.\n\nSpeaker 2: This doctor that you're assigned to, he's been pretty quick about everything today,\n\nSpeaker 1: so I told him to call you right now, give him a couple hours, we're going to wrap it up and then send the pills out ASAP, okay?\n\nSpeaker 2: I appreciate it.\n\nSpeaker 1: Yes sir.\n\nSpeaker 2: Thank you.\n\nSpeaker 1: Alright, have a great one.\n\nSpeaker 2: Alright, thanks.",
    "duration": 2800,
    "audioDuration": 74.12000274658203,
    "language": "english",
    "segments": [
      {
        "id": 0,
        "start": 0,
        "end": 17.399999618530273,
        "text": " Thanks for calling Viagra, this is Charles."
      },
      {
        "id": 1,
        "start": 17.399999618530273,
        "end": 27.959999084472656,
        "text": " Hi Charles, I ordered some Viagra AGB and it's telling me, I filled out all the information"
      },
      {
        "id": 2,
        "start": 27.959999084472656,
        "end": 33.560001373291016,
        "text": " and it's telling me they need a 5 second video of me and I'm not smart enough how to figure"
      },
      {
        "id": 3,
        "start": 33.560001373291016,
        "end": 37.560001373291016,
        "text": " out how to send you a 5 minute or 5 second video of me."
      },
      {
        "id": 4,
        "start": 37.560001373291016,
        "end": 38.560001373291016,
        "text": " Oh good."
      },
      {
        "id": 5,
        "start": 38.560001373291016,
        "end": 41.560001373291016,
        "text": " So they'll call the doctor or whatever and..."
      },
      {
        "id": 6,
        "start": 41.560001373291016,
        "end": 45.720001220703125,
        "text": " Yeah, let me do that for you, this is Kenton Doonman, right?"
      },
      {
        "id": 7,
        "start": 45.720001220703125,
        "end": 46.720001220703125,
        "text": " That's correct."
      },
      {
        "id": 8,
        "start": 46.720001220703125,
        "end": 53.63999938964844,
        "text": " Okay, please call at the end of the day today."
      },
      {
        "id": 9,
        "start": 53.63999938964844,
        "end": 58.52000045776367,
        "text": " This doctor that you're assigned to, he's been pretty quick about everything today,"
      },
      {
        "id": 10,
        "start": 58.52000045776367,
        "end": 64.08000183105469,
        "text": " so I told him to call you right now, give him a couple hours, we're going to wrap it"
      },
      {
        "id": 11,
        "start": 64.08000183105469,
        "end": 66.72000122070312,
        "text": " up and then send the pills out ASAP, okay?"
      },
      {
        "id": 12,
        "start": 66.72000122070312,
        "end": 67.72000122070312,
        "text": " I appreciate it."
      },
      {
        "id": 13,
        "start": 67.72000122070312,
        "end": 68.72000122070312,
        "text": " Yes sir."
      },
      {
        "id": 14,
        "start": 68.72000122070312,
        "end": 69.72000122070312,
        "text": " Thank you."
      },
      {
        "id": 15,
        "start": 69.72000122070312,
        "end": 70.72000122070312,
        "text": " Alright, have a great one."
      },
      {
        "id": 16,
        "start": 70.72000122070312,
        "end": 71.72000122070312,
        "text": " Alright, thanks."
      }
    ]
  },
  "notionPage": {
    "id": "30611d0a-101c-81b3-bb39-d5999f770545",
    "url": "https://www.notion.so/300000001241948-300000001731564-30611d0a101c81b3bb39d5999f770545"
  },
  "processedAt": "2026-02-13T19:03:25.272Z"
}