{
  "recording": {
    "name": "300000001217439-300000001707749-2298816326 by olivia@superbalife.com @ 10_20_10 AM.wav",
    "size": 362500,
    "modifyTime": 1769584036000,
    "remotePath": "/five9sftp/upload/SB CS/1_26_2026/300000001217439-300000001707749-2298816326 by olivia@superbalife.com @ 10_20_10 AM.wav",
    "uploadDate": "2026-01-28T07:07:16.000Z",
    "callId": "300000001217439-300000001707749",
    "agent": "olivia",
    "phoneNumber": "2298816326",
    "callTimestamp": "2026-01-28T10:20:10.000Z",
    "campaign": "test one"
  },
  "transcription": {
    "text": "Speaker 1: Thank you for calling BIACRA, this is Olivia speaking.\n\nSpeaker 2: Who do I have the pleasure of speaking with today?\n\nSpeaker 1: Hi, Samuel Smith.\n\nSpeaker 2: Hi, Samuel.\n\nSpeaker 1: How are you?\n\nSpeaker 2: I'm good.\n\nSpeaker 1: I've ordered some, well, I thought it was something different than this.\n\nSpeaker 2: I got some diapers from y'all.\n\nSpeaker 1: Yeah.\n\nSpeaker 2: I wanted to cancel getting any more because what I got just gives me migraines.\n\nSpeaker 1: Oh, I'm so sorry.\n\nSpeaker 2: It's fine.\n\nSpeaker 1: Okay.\n\nSpeaker 2: Yeah.\n\nSpeaker 1: No, that makes sense.\n\nSpeaker 2: Okay.\n\nSpeaker 1: Because I thought I was ordering BIACRA, the new one, the AVT,\n\nSpeaker 2: and I just got the 50 milligram generic,\n\nSpeaker 1: which I'm throwing in the trash.\n\nSpeaker 2: It don't help me now.\n\nSpeaker 1: Yeah.\n\nSpeaker 2: I'm so sorry to hear that.\n\nSpeaker 1: Yeah, let me look into this for you.\n\nSpeaker 2: What is your date of birth, Samuel?\n\nSpeaker 1: That was 9-9-1953.\n\nSpeaker 2: Great.\n\nSpeaker 1: And you're located in Adel, Georgia?\n\nSpeaker 2: Yeah, Adel, Georgia.\n\nSpeaker 1: Adel, Georgia.\n\nSpeaker 2: Okay, great.\n\nSpeaker 1: Yeah, so I do see your prescription here.\n\nSpeaker 2: Okay.\n\nSpeaker 1: Yeah, so you're saying you didn't receive the AGV.\n\nSpeaker 2: Is that right?\n\nSpeaker 1: Well, what I have, it says 50 milligram generic BIACRA.\n\nSpeaker 2: I figured it would say ABG on it somewhere if that's what I got.\n\nSpeaker 1: It was supposed to be it.\n\nSpeaker 2: Yeah.\n\nSpeaker 1: Okay.\n\nSpeaker 2: Well, what I would like to do, if that's what has happened,\n\nSpeaker 1: I would be happy to send you out a replacement of the AGV,\n\nSpeaker 2: because it is a great product.\n\nSpeaker 1: It is a superior product to the generic.\n\nSpeaker 2: And most importantly,\n\nSpeaker 1: it's been specifically formulated to cut out the side effects of sinus\n\nSpeaker 2: agitation and headache.\n\nSpeaker 1: Okay.\n\nSpeaker 2: Well, if you could send me that,\n\nSpeaker 1: how much more is it going to cost me to get that?\n\nSpeaker 2: So I will send it as a replacement for free on that,\n\nSpeaker 1: because, yeah, you didn't receive the right product.\n\nSpeaker 2: Okay.\n\nSpeaker 1: So I'm going to send it to you at 50 milligrams,\n\nSpeaker 2: because that's what you've already been approved for.\n\nSpeaker 1: Can I ship it to 1224 Joiner Road, Adel, Georgia, 31620?\n\nSpeaker 2: Yes, ma'am.\n\nSpeaker 1: Okay, great.\n\nSpeaker 2: So this should be out to you, I mean,\n\nSpeaker 1: pending this whatever snow or cold storm that's supposedly around.\n\nSpeaker 2: But this should usually get to you within two to four days,\n\nSpeaker 1: because you're pretty close to air shipping.\n\nSpeaker 2: But, yeah, it'll probably get to you by the end of the week at the latest.\n\nSpeaker 1: Just a reminder, make sure to take it on an empty stomach.\n\nSpeaker 2: That's really important.\n\nSpeaker 1: And then you want to avoid alcohol and caffeine.\n\nSpeaker 2: When you take it, just because caffeine and alcohol restrict blood flow,\n\nSpeaker 1: and you want more, not less.\n\nSpeaker 2: Okay.\n\nSpeaker 1: Well, alcohol is a problem, and I have to worry about caffeine.\n\nSpeaker 2: So I'll put it back on caffeine.\n\nSpeaker 1: Okay, great.\n\nSpeaker 2: I'll put it on whatever I need to do.\n\nSpeaker 1: Yeah.\n\nSpeaker 2: All right.\n\nSpeaker 1: Well, thank you so much, Samuel.\n\nSpeaker 2: I hope you love them, and I hope you have a great day.\n\nSpeaker 1: Thank you, ma'am.\n\nSpeaker 2: Okay, yeah.\n\nSpeaker 1: Have a great day.\n\nSpeaker 2: Bye-bye.\n\nSpeaker 1: Bye.",
    "duration": 10997,
    "language": "english",
    "segments": [
      {
        "id": 0,
        "start": 0,
        "end": 6,
        "text": " Thank you for calling BIACRA, this is Olivia speaking."
      },
      {
        "id": 1,
        "start": 6,
        "end": 9,
        "text": " Who do I have the pleasure of speaking with today?"
      },
      {
        "id": 2,
        "start": 9,
        "end": 11,
        "text": " Hi, Samuel Smith."
      },
      {
        "id": 3,
        "start": 11,
        "end": 13,
        "text": " Hi, Samuel."
      },
      {
        "id": 4,
        "start": 13,
        "end": 14,
        "text": " How are you?"
      },
      {
        "id": 5,
        "start": 14,
        "end": 16,
        "text": " I'm good."
      },
      {
        "id": 6,
        "start": 16,
        "end": 23,
        "text": " I've ordered some, well, I thought it was something different than this."
      },
      {
        "id": 7,
        "start": 23,
        "end": 25,
        "text": " I got some diapers from y'all."
      },
      {
        "id": 8,
        "start": 25,
        "end": 26,
        "text": " Yeah."
      },
      {
        "id": 9,
        "start": 26,
        "end": 33,
        "text": " I wanted to cancel getting any more because what I got just gives me migraines."
      },
      {
        "id": 10,
        "start": 33,
        "end": 35,
        "text": " Oh, I'm so sorry."
      },
      {
        "id": 11,
        "start": 35,
        "end": 36,
        "text": " It's fine."
      },
      {
        "id": 12,
        "start": 36,
        "end": 37,
        "text": " Okay."
      },
      {
        "id": 13,
        "start": 37,
        "end": 38,
        "text": " Yeah."
      },
      {
        "id": 14,
        "start": 38,
        "end": 39,
        "text": " No, that makes sense."
      },
      {
        "id": 15,
        "start": 39,
        "end": 42,
        "text": " Okay."
      },
      {
        "id": 16,
        "start": 42,
        "end": 46,
        "text": " Because I thought I was ordering BIACRA, the new one, the AVT,"
      },
      {
        "id": 17,
        "start": 46,
        "end": 50,
        "text": " and I just got the 50 milligram generic,"
      },
      {
        "id": 18,
        "start": 50,
        "end": 54,
        "text": " which I'm throwing in the trash."
      },
      {
        "id": 19,
        "start": 54,
        "end": 57,
        "text": " It don't help me now."
      },
      {
        "id": 20,
        "start": 57,
        "end": 60,
        "text": " Yeah."
      },
      {
        "id": 21,
        "start": 60,
        "end": 64,
        "text": " I'm so sorry to hear that."
      },
      {
        "id": 22,
        "start": 64,
        "end": 66,
        "text": " Yeah, let me look into this for you."
      },
      {
        "id": 23,
        "start": 66,
        "end": 68,
        "text": " What is your date of birth, Samuel?"
      },
      {
        "id": 24,
        "start": 68,
        "end": 72,
        "text": " That was 9-9-1953."
      },
      {
        "id": 25,
        "start": 72,
        "end": 73,
        "text": " Great."
      },
      {
        "id": 26,
        "start": 73,
        "end": 75,
        "text": " And you're located in Adel, Georgia?"
      },
      {
        "id": 27,
        "start": 75,
        "end": 77,
        "text": " Yeah, Adel, Georgia."
      },
      {
        "id": 28,
        "start": 77,
        "end": 78,
        "text": " Adel, Georgia."
      },
      {
        "id": 29,
        "start": 78,
        "end": 79,
        "text": " Okay, great."
      },
      {
        "id": 30,
        "start": 79,
        "end": 82,
        "text": " Yeah, so I do see your prescription here."
      },
      {
        "id": 31,
        "start": 82,
        "end": 85,
        "text": " Okay."
      },
      {
        "id": 32,
        "start": 85,
        "end": 93,
        "text": " Yeah, so you're saying you didn't receive the AGV."
      },
      {
        "id": 33,
        "start": 93,
        "end": 94,
        "text": " Is that right?"
      },
      {
        "id": 34,
        "start": 94,
        "end": 99,
        "text": " Well, what I have, it says 50 milligram generic BIACRA."
      },
      {
        "id": 35,
        "start": 99,
        "end": 103,
        "text": " I figured it would say ABG on it somewhere if that's what I got."
      },
      {
        "id": 36,
        "start": 103,
        "end": 105,
        "text": " It was supposed to be it."
      },
      {
        "id": 37,
        "start": 105,
        "end": 106,
        "text": " Yeah."
      },
      {
        "id": 38,
        "start": 106,
        "end": 108,
        "text": " Okay."
      },
      {
        "id": 39,
        "start": 108,
        "end": 113,
        "text": " Well, what I would like to do, if that's what has happened,"
      },
      {
        "id": 40,
        "start": 113,
        "end": 119,
        "text": " I would be happy to send you out a replacement of the AGV,"
      },
      {
        "id": 41,
        "start": 119,
        "end": 122,
        "text": " because it is a great product."
      },
      {
        "id": 42,
        "start": 122,
        "end": 127,
        "text": " It is a superior product to the generic."
      },
      {
        "id": 43,
        "start": 127,
        "end": 129,
        "text": " And most importantly,"
      },
      {
        "id": 44,
        "start": 129,
        "end": 134,
        "text": " it's been specifically formulated to cut out the side effects of sinus"
      },
      {
        "id": 45,
        "start": 134,
        "end": 136,
        "text": " agitation and headache."
      },
      {
        "id": 46,
        "start": 136,
        "end": 137,
        "text": " Okay."
      },
      {
        "id": 47,
        "start": 137,
        "end": 140,
        "text": " Well, if you could send me that,"
      },
      {
        "id": 48,
        "start": 140,
        "end": 142,
        "text": " how much more is it going to cost me to get that?"
      },
      {
        "id": 49,
        "start": 142,
        "end": 147,
        "text": " So I will send it as a replacement for free on that,"
      },
      {
        "id": 50,
        "start": 147,
        "end": 149,
        "text": " because, yeah, you didn't receive the right product."
      },
      {
        "id": 51,
        "start": 149,
        "end": 150,
        "text": " Okay."
      },
      {
        "id": 52,
        "start": 150,
        "end": 154,
        "text": " So I'm going to send it to you at 50 milligrams,"
      },
      {
        "id": 53,
        "start": 154,
        "end": 156,
        "text": " because that's what you've already been approved for."
      },
      {
        "id": 54,
        "start": 156,
        "end": 165,
        "text": " Can I ship it to 1224 Joiner Road, Adel, Georgia, 31620?"
      },
      {
        "id": 55,
        "start": 165,
        "end": 166,
        "text": " Yes, ma'am."
      },
      {
        "id": 56,
        "start": 166,
        "end": 168,
        "text": " Okay, great."
      },
      {
        "id": 57,
        "start": 168,
        "end": 171,
        "text": " So this should be out to you, I mean,"
      },
      {
        "id": 58,
        "start": 171,
        "end": 175,
        "text": " pending this whatever snow or cold storm that's supposedly around."
      },
      {
        "id": 59,
        "start": 175,
        "end": 180,
        "text": " But this should usually get to you within two to four days,"
      },
      {
        "id": 60,
        "start": 180,
        "end": 182,
        "text": " because you're pretty close to air shipping."
      },
      {
        "id": 61,
        "start": 182,
        "end": 186,
        "text": " But, yeah, it'll probably get to you by the end of the week at the latest."
      },
      {
        "id": 62,
        "start": 186,
        "end": 190,
        "text": " Just a reminder, make sure to take it on an empty stomach."
      },
      {
        "id": 63,
        "start": 190,
        "end": 191,
        "text": " That's really important."
      },
      {
        "id": 64,
        "start": 192,
        "end": 196,
        "text": " And then you want to avoid alcohol and caffeine."
      },
      {
        "id": 65,
        "start": 196,
        "end": 200,
        "text": " When you take it, just because caffeine and alcohol restrict blood flow,"
      },
      {
        "id": 66,
        "start": 200,
        "end": 202,
        "text": " and you want more, not less."
      },
      {
        "id": 67,
        "start": 202,
        "end": 203,
        "text": " Okay."
      },
      {
        "id": 68,
        "start": 203,
        "end": 206,
        "text": " Well, alcohol is a problem, and I have to worry about caffeine."
      },
      {
        "id": 69,
        "start": 206,
        "end": 208,
        "text": " So I'll put it back on caffeine."
      },
      {
        "id": 70,
        "start": 208,
        "end": 209,
        "text": " Okay, great."
      },
      {
        "id": 71,
        "start": 209,
        "end": 210,
        "text": " I'll put it on whatever I need to do."
      },
      {
        "id": 72,
        "start": 210,
        "end": 211,
        "text": " Yeah."
      },
      {
        "id": 73,
        "start": 211,
        "end": 212,
        "text": " All right."
      },
      {
        "id": 74,
        "start": 212,
        "end": 214,
        "text": " Well, thank you so much, Samuel."
      },
      {
        "id": 75,
        "start": 214,
        "end": 216,
        "text": " I hope you love them, and I hope you have a great day."
      },
      {
        "id": 76,
        "start": 216,
        "end": 218,
        "text": " Thank you, ma'am."
      },
      {
        "id": 77,
        "start": 218,
        "end": 219,
        "text": " Okay, yeah."
      },
      {
        "id": 78,
        "start": 219,
        "end": 220,
        "text": " Have a great day."
      },
      {
        "id": 79,
        "start": 220,
        "end": 221,
        "text": " Bye-bye."
      },
      {
        "id": 80,
        "start": 221,
        "end": 222,
        "text": " Bye."
      }
    ]
  },
  "notionPage": {
    "id": "2f611d0a-101c-8160-b006-fad796b02a95",
    "url": "https://www.notion.so/300000001217439-300000001707749-2f611d0a101c8160b006fad796b02a95"
  },
  "processedAt": "2026-01-28T15:38:26.282Z"
}