{
  "recording": {
    "name": "300000001216448-300000001705881-6085203747 by  @ 2_03_28 PM_CallStudio.wav",
    "size": 24306,
    "modifyTime": 1769586437000,
    "remotePath": "/five9sftp/upload/SB CS/1_23_2026/300000001216448-300000001705881-6085203747 by  @ 2_03_28 PM_CallStudio.wav",
    "uploadDate": "2026-01-28T07:47:17.000Z",
    "callId": "300000001216448-300000001705881",
    "phoneNumber": "6085203747",
    "callTimestamp": "2026-01-28T07:47:17.000Z",
    "campaign": "test one"
  },
  "transcription": {
    "text": "Speaker 1: To help get you to the right agent, please state the reason for your call, speak loudly.\n\nSpeaker 2: And clearly.\n\nSpeaker 1: Para Español Marco numero uno.\n\nSpeaker 2: I'm trying to find out, I'm trying to find out where my field's at.\n\nSpeaker 1: Thanks.\n\nSpeaker 2: Transferring to agent.",
    "duration": 961,
    "language": "english",
    "segments": [
      {
        "id": 0,
        "start": 0,
        "end": 6.239999771118164,
        "text": " To help get you to the right agent, please state the reason for your call, speak loudly"
      },
      {
        "id": 1,
        "start": 6.239999771118164,
        "end": 7.239999771118164,
        "text": " and clearly."
      },
      {
        "id": 2,
        "start": 7.239999771118164,
        "end": 8.239999771118164,
        "text": " Para Español Marco numero uno."
      },
      {
        "id": 3,
        "start": 8.239999771118164,
        "end": 13.399999618530273,
        "text": " I'm trying to find out, I'm trying to find out where my field's at."
      },
      {
        "id": 4,
        "start": 13.399999618530273,
        "end": 14.399999618530273,
        "text": " Thanks."
      },
      {
        "id": 5,
        "start": 14.399999618530273,
        "end": 14.600000381469727,
        "text": " Transferring to agent."
      }
    ]
  },
  "notionPage": {
    "id": "2f611d0a-101c-814c-807b-cab9ce4c319d",
    "url": "https://www.notion.so/300000001216448-300000001705881-2f611d0a101c814c807bcab9ce4c319d"
  },
  "processedAt": "2026-01-28T13:43:58.758Z"
}